bib_ami/__init__.py
bib_ami/__main__.py
bib_ami/bibtex_manager.py
bib_ami/cli.py
bib_ami/cross_ref_client.py
bib_ami/diff_utils.py
bib_ami/ingestor.py
bib_ami/log_setup.py
bib_ami/metadata_refresher.py
bib_ami/reconciler.py
bib_ami/reporter.py
bib_ami/triage.py
bib_ami/validator.py
bib_ami/writer.py
bib_ami-0.16.0.dist-info/licenses/LICENSE
bib_ami-0.16.0.dist-info/METADATA
bib_ami-0.16.0.dist-info/WHEEL
bib_ami-0.16.0.dist-info/entry_points.txt
bib_ami-0.16.0.dist-info/top_level.txt
bib_ami-0.16.0.dist-info/RECORD
