Metadata-Version: 2.4
Name: bib-ami
Version: 0.16.0
Summary: A command-line tool for improving the integrity of BibTeX bibliographies
Author-email: Rolf Carlson <hrolfrc@gmail.com>
License: MIT
Project-URL: Homepage, https://github.com/hrolfrc/bib-ami
Project-URL: Repository, https://github.com/hrolfrc/bib-ami
Project-URL: Documentation, https://bib-ami.readthedocs.io
Classifier: Programming Language :: Python :: 3
Classifier: License :: OSI Approved :: MIT License
Classifier: Operating System :: OS Independent
Classifier: Intended Audience :: Science/Research
Classifier: Topic :: Scientific/Engineering :: Information Analysis
Requires-Python: >=3.7
License-File: LICENSE
Requires-Dist: bibtexparser>=1.4.1
Requires-Dist: requests>=2.31.0
Requires-Dist: fuzzywuzzy>=0.18.0
Requires-Dist: python-Levenshtein>=0.25.0
Provides-Extra: dev
Requires-Dist: pytest>=7.4.0; extra == "dev"
Requires-Dist: pytest-cov>=4.1.0; extra == "dev"
Requires-Dist: pytest-mock>=3.14.0; extra == "dev"
Requires-Dist: sphinx>=7.0.0; extra == "dev"
Requires-Dist: sphinx_rtd_theme>=2.0.0; extra == "dev"
Dynamic: license-file
